vibepython/__init__.py
vibepython/__main__.py
vibepython/main.py
vibepython/execute/__init__.py
vibepython/execute/execute.py
vibepython/execute/models.py
vibepython/history/__init__.py
vibepython/history/models.py
vibepython/history/state.py
vibepython/providers/__init__.py
vibepython/providers/handler_gpt4free/__init__.py
vibepython/providers/handler_gpt4free/generate.py
vibepython/providers/handler_ollama/__init__.py
vibepython/providers/handler_ollama/generate.py
vibepython/providers/handler_openai/__init__.py
vibepython/providers/handler_openai/generate.py
vibepython-0.0.5.dist-info/METADATA
vibepython-0.0.5.dist-info/WHEEL
vibepython-0.0.5.dist-info/entry_points.txt
vibepython-0.0.5.dist-info/licenses/LICENSE
vibepython-0.0.5.dist-info/RECORD
