Metadata-Version: 2.4
Name: vibepython
Version: 0.0.5
Summary: 🚀 Python vibe: Unleash the Magic of AI-Powered Coding Wizardry! 🌟
Project-URL: Homepage, https://github.com/oldtyt/vibepython
Project-URL: Source, https://github.com/oldtyt/vibepython
Author: OldTyT
License-File: LICENSE
Classifier: License :: OSI Approved :: MIT License
Classifier: Operating System :: OS Independent
Classifier: Programming Language :: Python :: 3
Requires-Python: >=3.8
Requires-Dist: g4f[slim]<0.7.0.0,>=0.6.0.1
Requires-Dist: loguru<1.0.0,>=0.7.0
Requires-Dist: openai<2.0.0,>=1.56.0
Requires-Dist: pydantic-core<3.0.0,>=2.20.0
Requires-Dist: pydantic-settings<3.0.0,>=2.4.0
Requires-Dist: pydantic<3.0.0,>=2.8.0
